[{"instanceName":"vol-7710b98f","region":"us-west-1","post_date":"1448999580000","metric_type":"VolumeReadOps","metric_value":0,"unit":"Count"},{"instanceName":"vol-7710b98f","region":"us-west-1","post_date":"1449028380000","metric_type":"VolumeReadOps","metric_value":0,"unit":"Count"},{"instanceName":"vol-7710b98f","region":"us-west-1","post_date":"1449021180000","metric_type":"VolumeReadOps","metric_value":0,"unit":"Count"},{"instanceName":"vol-7710b98f","region":"us-west-1","post_date":"1449013980000","metric_type":"VolumeReadOps","metric_value":0,"unit":"Count"},{"instanceName":"vol-7710b98f","region":"us-west-1","post_date":"1448970780000","metric_type":"VolumeReadOps","metric_value":0,"unit":"Count"},{"instanceName":"vol-7710b98f","region":"us-west-1","post_date":"1448988780000","metric_type":"VolumeReadOps","metric_value":0,"unit":"Count"},{"instanceName":"vol-7710b98f","region":"us-west-1","post_date":"1448952780000","metric_type":"VolumeReadOps","metric_value":0,"unit":"Count"},{"instanceName":"vol-7710b98f","region":"us-west-1","post_date":"1448967180000","metric_type":"VolumeReadOps","metric_value":0,"unit":"Count"},{"instanceName":"vol-7710b98f","region":"us-west-1","post_date":"1448963580000","metric_type":"VolumeReadOps","metric_value":0,"unit":"Count"},{"instanceName":"vol-7710b98f","region":"us-west-1","post_date":"1448959980000","metric_type":"VolumeReadOps","metric_value":0,"unit":"Count"},{"instanceName":"vol-7710b98f","region":"us-west-1","post_date":"1449003180000","metric_type":"VolumeReadOps","metric_value":0,"unit":"Count"},{"instanceName":"vol-7710b98f","region":"us-west-1","post_date":"1449024780000","metric_type":"VolumeReadOps","metric_value":0,"unit":"Count"},{"instanceName":"vol-7710b98f","region":"us-west-1","post_date":"1448985180000","metric_type":"VolumeReadOps","metric_value":0,"unit":"Count"},{"instanceName":"vol-7710b98f","region":"us-west-1","post_date":"1448949180000","metric_type":"VolumeReadOps","metric_value":0,"unit":"Count"},{"instanceName":"vol-7710b98f","region":"us-west-1","post_date":"1448981580000","metric_type":"VolumeReadOps","metric_value":0,"unit":"Count"},{"instanceName":"vol-7710b98f","region":"us-west-1","post_date":"1448945580000","metric_type":"VolumeReadOps","metric_value":0,"unit":"Count"},{"instanceName":"vol-7710b98f","region":"us-west-1","post_date":"1449006780000","metric_type":"VolumeReadOps","metric_value":0,"unit":"Count"},{"instanceName":"vol-7710b98f","region":"us-west-1","post_date":"1448995980000","metric_type":"VolumeReadOps","metric_value":0,"unit":"Count"},{"instanceName":"vol-7710b98f","region":"us-west-1","post_date":"1448974380000","metric_type":"VolumeReadOps","metric_value":0,"unit":"Count"},{"instanceName":"vol-7710b98f","region":"us-west-1","post_date":"1448956380000","metric_type":"VolumeReadOps","metric_value":0,"unit":"Count"},{"instanceName":"vol-7710b98f","region":"us-west-1","post_date":"1449010380000","metric_type":"VolumeReadOps","metric_value":0,"unit":"Count"},{"instanceName":"vol-7710b98f","region":"us-west-1","post_date":"1448977980000","metric_type":"VolumeReadOps","metric_value":0,"unit":"Count"},{"instanceName":"vol-7710b98f","region":"us-west-1","post_date":"1449017580000","metric_type":"VolumeReadOps","metric_value":0,"unit":"Count"},{"instanceName":"vol-7710b98f","region":"us-west-1","post_date":"1448992380000","metric_type":"VolumeReadOps","metric_value":0,"unit":"Count"},{"instanceName":"vol-b910b941","region":"us-west-1","post_date":"1448999580000","metric_type":"VolumeReadOps","metric_value":0,"unit":"Count"},{"instanceName":"vol-b910b941","region":"us-west-1","post_date":"1449028380000","metric_type":"VolumeReadOps","metric_value":0,"unit":"Count"},{"instanceName":"vol-b910b941","region":"us-west-1","post_date":"1449021180000","metric_type":"VolumeReadOps","metric_value":0,"unit":"Count"},{"instanceName":"vol-b910b941","region":"us-west-1","post_date":"1449013980000","metric_type":"VolumeReadOps","metric_value":0,"unit":"Count"},{"instanceName":"vol-b910b941","region":"us-west-1","post_date":"1448970780000","metric_type":"VolumeReadOps","metric_value":0,"unit":"Count"},{"instanceName":"vol-b910b941","region":"us-west-1","post_date":"1448988780000","metric_type":"VolumeReadOps","metric_value":0,"unit":"Count"},{"instanceName":"vol-b910b941","region":"us-west-1","post_date":"1448952780000","metric_type":"VolumeReadOps","metric_value":12.416666666666666,"unit":"Count"},{"instanceName":"vol-b910b941","region":"us-west-1","post_date":"1448967180000","metric_type":"VolumeReadOps","metric_value":0,"unit":"Count"},{"instanceName":"vol-b910b941","region":"us-west-1","post_date":"1448963580000","metric_type":"VolumeReadOps","metric_value":0,"unit":"Count"},{"instanceName":"vol-b910b941","region":"us-west-1","post_date":"1448959980000","metric_type":"VolumeReadOps","metric_value":0,"unit":"Count"},{"instanceName":"vol-b910b941","region":"us-west-1","post_date":"1449003180000","metric_type":"VolumeReadOps","metric_value":0,"unit":"Count"},{"instanceName":"vol-b910b941","region":"us-west-1","post_date":"1449024780000","metric_type":"VolumeReadOps","metric_value":0,"unit":"Count"},{"instanceName":"vol-b910b941","region":"us-west-1","post_date":"1448985180000","metric_type":"VolumeReadOps","metric_value":0,"unit":"Count"},{"instanceName":"vol-b910b941","region":"us-west-1","post_date":"1448949180000","metric_type":"VolumeReadOps","metric_value":0,"unit":"Count"},{"instanceName":"vol-b910b941","region":"us-west-1","post_date":"1448981580000","metric_type":"VolumeReadOps","metric_value":0,"unit":"Count"},{"instanceName":"vol-b910b941","region":"us-west-1","post_date":"1448945580000","metric_type":"VolumeReadOps","metric_value":0,"unit":"Count"},{"instanceName":"vol-b910b941","region":"us-west-1","post_date":"1449006780000","metric_type":"VolumeReadOps","metric_value":0,"unit":"Count"},{"instanceName":"vol-b910b941","region":"us-west-1","post_date":"1448995980000","metric_type":"VolumeReadOps","metric_value":0,"unit":"Count"},{"instanceName":"vol-b910b941","region":"us-west-1","post_date":"1448974380000","metric_type":"VolumeReadOps","metric_value":0,"unit":"Count"},{"instanceName":"vol-b910b941","region":"us-west-1","post_date":"1448956380000","metric_type":"VolumeReadOps","metric_value":0,"unit":"Count"},{"instanceName":"vol-b910b941","region":"us-west-1","post_date":"1449010380000","metric_type":"VolumeReadOps","metric_value":0,"unit":"Count"},{"instanceName":"vol-b910b941","region":"us-west-1","post_date":"1448977980000","metric_type":"VolumeReadOps","metric_value":0,"unit":"Count"},{"instanceName":"vol-b910b941","region":"us-west-1","post_date":"1449017580000","metric_type":"VolumeReadOps","metric_value":0,"unit":"Count"},{"instanceName":"vol-b910b941","region":"us-west-1","post_date":"1448992380000","metric_type":"VolumeReadOps","metric_value":0,"unit":"Count"},{"instanceName":"vol-6443e89c","region":"us-west-1","post_date":"1448999580000","metric_type":"VolumeReadOps","metric_value":0,"unit":"Count"},{"instanceName":"vol-6443e89c","region":"us-west-1","post_date":"1449028380000","metric_type":"VolumeReadOps","metric_value":0,"unit":"Count"},{"instanceName":"vol-6443e89c","region":"us-west-1","post_date":"1449021180000","metric_type":"VolumeReadOps","metric_value":0,"unit":"Count"},{"instanceName":"vol-6443e89c","region":"us-west-1","post_date":"1449013980000","metric_type":"VolumeReadOps","metric_value":0,"unit":"Count"},{"instanceName":"vol-6443e89c","region":"us-west-1","post_date":"1448970780000","metric_type":"VolumeReadOps","metric_value":0,"unit":"Count"},{"instanceName":"vol-6443e89c","region":"us-west-1","post_date":"1448988780000","metric_type":"VolumeReadOps","metric_value":0,"unit":"Count"},{"instanceName":"vol-6443e89c","region":"us-west-1","post_date":"1448952780000","metric_type":"VolumeReadOps","metric_value":0,"unit":"Count"},{"instanceName":"vol-6443e89c","region":"us-west-1","post_date":"1448967180000","metric_type":"VolumeReadOps","metric_value":0,"unit":"Count"},{"instanceName":"vol-6443e89c","region":"us-west-1","post_date":"1448963580000","metric_type":"VolumeReadOps","metric_value":0,"unit":"Count"},{"instanceName":"vol-6443e89c","region":"us-west-1","post_date":"1448959980000","metric_type":"VolumeReadOps","metric_value":0,"unit":"Count"},{"instanceName":"vol-6443e89c","region":"us-west-1","post_date":"1449003180000","metric_type":"VolumeReadOps","metric_value":0,"unit":"Count"},{"instanceName":"vol-6443e89c","region":"us-west-1","post_date":"1449024780000","metric_type":"VolumeReadOps","metric_value":0,"unit":"Count"},{"instanceName":"vol-6443e89c","region":"us-west-1","post_date":"1448985180000","metric_type":"VolumeReadOps","metric_value":0,"unit":"Count"},{"instanceName":"vol-6443e89c","region":"us-west-1","post_date":"1448949180000","metric_type":"VolumeReadOps","metric_value":0,"unit":"Count"},{"instanceName":"vol-6443e89c","region":"us-west-1","post_date":"1448981580000","metric_type":"VolumeReadOps","metric_value":0,"unit":"Count"},{"instanceName":"vol-6443e89c","region":"us-west-1","post_date":"1448945580000","metric_type":"VolumeReadOps","metric_value":0,"unit":"Count"},{"instanceName":"vol-6443e89c","region":"us-west-1","post_date":"1449006780000","metric_type":"VolumeReadOps","metric_value":0,"unit":"Count"},{"instanceName":"vol-6443e89c","region":"us-west-1","post_date":"1448995980000","metric_type":"VolumeReadOps","metric_value":0,"unit":"Count"},{"instanceName":"vol-6443e89c","region":"us-west-1","post_date":"1448974380000","metric_type":"VolumeReadOps","metric_value":0,"unit":"Count"},{"instanceName":"vol-6443e89c","region":"us-west-1","post_date":"1448956380000","metric_type":"VolumeReadOps","metric_value":0,"unit":"Count"},{"instanceName":"vol-6443e89c","region":"us-west-1","post_date":"1449010380000","metric_type":"VolumeReadOps","metric_value":0,"unit":"Count"},{"instanceName":"vol-6443e89c","region":"us-west-1","post_date":"1448977980000","metric_type":"VolumeReadOps","metric_value":0,"unit":"Count"},{"instanceName":"vol-6443e89c","region":"us-west-1","post_date":"1449017580000","metric_type":"VolumeReadOps","metric_value":0,"unit":"Count"},{"instanceName":"vol-6443e89c","region":"us-west-1","post_date":"1448992380000","metric_type":"VolumeReadOps","metric_value":0,"unit":"Count"},{"instanceName":"vol-3042e9c8","region":"us-west-1","post_date":"1448999580000","metric_type":"VolumeReadOps","metric_value":0,"unit":"Count"},{"instanceName":"vol-3042e9c8","region":"us-west-1","post_date":"1449028380000","metric_type":"VolumeReadOps","metric_value":0,"unit":"Count"},{"instanceName":"vol-3042e9c8","region":"us-west-1","post_date":"1449021180000","metric_type":"VolumeReadOps","metric_value":0,"unit":"Count"},{"instanceName":"vol-3042e9c8","region":"us-west-1","post_date":"1449013980000","metric_type":"VolumeReadOps","metric_value":0,"unit":"Count"},{"instanceName":"vol-3042e9c8","region":"us-west-1","post_date":"1448970780000","metric_type":"VolumeReadOps","metric_value":0,"unit":"Count"},{"instanceName":"vol-3042e9c8","region":"us-west-1","post_date":"1448988780000","metric_type":"VolumeReadOps","metric_value":0,"unit":"Count"},{"instanceName":"vol-3042e9c8","region":"us-west-1","post_date":"1448952780000","metric_type":"VolumeReadOps","metric_value":0,"unit":"Count"},{"instanceName":"vol-3042e9c8","region":"us-west-1","post_date":"1448967180000","metric_type":"VolumeReadOps","metric_value":0,"unit":"Count"},{"instanceName":"vol-3042e9c8","region":"us-west-1","post_date":"1448963580000","metric_type":"VolumeReadOps","metric_value":0,"unit":"Count"},{"instanceName":"vol-3042e9c8","region":"us-west-1","post_date":"1448959980000","metric_type":"VolumeReadOps","metric_value":0,"unit":"Count"},{"instanceName":"vol-3042e9c8","region":"us-west-1","post_date":"1449003180000","metric_type":"VolumeReadOps","metric_value":0,"unit":"Count"},{"instanceName":"vol-3042e9c8","region":"us-west-1","post_date":"1449024780000","metric_type":"VolumeReadOps","metric_value":0,"unit":"Count"},{"instanceName":"vol-3042e9c8","region":"us-west-1","post_date":"1448985180000","metric_type":"VolumeReadOps","metric_value":0,"unit":"Count"},{"instanceName":"vol-3042e9c8","region":"us-west-1","post_date":"1448949180000","metric_type":"VolumeReadOps","metric_value":0,"unit":"Count"},{"instanceName":"vol-3042e9c8","region":"us-west-1","post_date":"1448981580000","metric_type":"VolumeReadOps","metric_value":0,"unit":"Count"},{"instanceName":"vol-3042e9c8","region":"us-west-1","post_date":"1448945580000","metric_type":"VolumeReadOps","metric_value":0,"unit":"Count"},{"instanceName":"vol-3042e9c8","region":"us-west-1","post_date":"1449006780000","metric_type":"VolumeReadOps","metric_value":0,"unit":"Count"},{"instanceName":"vol-3042e9c8","region":"us-west-1","post_date":"1448995980000","metric_type":"VolumeReadOps","metric_value":0,"unit":"Count"},{"instanceName":"vol-3042e9c8","region":"us-west-1","post_date":"1448974380000","metric_type":"VolumeReadOps","metric_value":0,"unit":"Count"},{"instanceName":"vol-3042e9c8","region":"us-west-1","post_date":"1448956380000","metric_type":"VolumeReadOps","metric_value":0,"unit":"Count"},{"instanceName":"vol-3042e9c8","region":"us-west-1","post_date":"1449010380000","metric_type":"VolumeReadOps","metric_value":0,"unit":"Count"},{"instanceName":"vol-3042e9c8","region":"us-west-1","post_date":"1448977980000","metric_type":"VolumeReadOps","metric_value":0,"unit":"Count"},{"instanceName":"vol-3042e9c8","region":"us-west-1","post_date":"1449017580000","metric_type":"VolumeReadOps","metric_value":0,"unit":"Count"},{"instanceName":"vol-3042e9c8","region":"us-west-1","post_date":"1448992380000","metric_type":"VolumeReadOps","metric_value":0,"unit":"Count"}]